langchain_airbyte/__init__.py
langchain_airbyte/document_loaders.py
langchain_airbyte/py.typed
gigachain_airbyte-0.1.1.dist-info/LICENSE
gigachain_airbyte-0.1.1.dist-info/METADATA
gigachain_airbyte-0.1.1.dist-info/WHEEL
gigachain_airbyte-0.1.1.dist-info/RECORD
